elev/__init__.py
elev/functions.py
elev_orbits_and_shadows-1.1.dist-info/LICENSE.txt
elev_orbits_and_shadows-1.1.dist-info/METADATA
elev_orbits_and_shadows-1.1.dist-info/WHEEL
elev_orbits_and_shadows-1.1.dist-info/top_level.txt
elev_orbits_and_shadows-1.1.dist-info/RECORD
