Metadata-Version: 2.1
Name: elev-orbits-and-shadows
Version: 1.1
Summary: Python3 package drawing orbits and shadows of Euclidean and Lorentzian electro-vacuum (elev) spacetimes
Home-page: https://github.com/arthur-garnier/euclidean_orbits_and_shadows
Author: Arthur Garnier
Author-email: <arthur.garnier@math.cnrs.fr>
License: UNKNOWN
Keywords: python,euclidean spacetime,instanton,reissner-nordstrom,bertotti-robinson,schwarzschild,black hole,orbit,black hole shadowing,spacetime shadowing,backward ray-tracing,gif
Platform: UNKNOWN
Classifier: Development Status :: 3 - Alpha
Classifier: Intended Audience :: Education
Classifier: Intended Audience :: Science/Research
Classifier: Programming Language :: Python :: 3
Classifier: Operating System :: Unix
Classifier: Operating System :: MacOS :: MacOS X
Classifier: Operating System :: Microsoft :: Windows
Classifier: License :: OSI Approved :: GNU General Public License v3 (GPLv3)
Requires-Python: >=3.10
License-File: LICENSE.txt
Requires-Dist: imageio (>=2.36)
Requires-Dist: opencv-python (>=4.10)
